{
    "Time": "2021-06-23T21:00:00Z",
    "Pressure": [
      1000,
      975,
      950,
      925,
      900,
      850,
      800,
      750,
      700,
      650,
      600,
      550,
      500,
      450,
      400,
      350,
      300,
      250,
      200,
      150,
      100,
      70,
      50,
      30,
      20,
      10,
      7,
      5,
      3,
      2,
      1
    ],
    "Height": [
      341,
      1066,
      1808,
      2567,
      3343,
      4958,
      6665,
      8463,
      10370,
      12391,
      14542,
      16847,
      19323,
      22004,
      24920,
      28129,
      31748,
      35920,
      40850,
      46878,
      54933,
      61840,
      68551,
      79187,
      87790,
      103061,
      111174,
      119012,
      131259,
      141320,
      158923
    ],
    "Temp": [
      24,
      22,
      20,
      20,
      20,
      19,
      17,
      15,
      12,
      8,
      4,
      0,
      -5,
      -11,
      -19,
      -26,
      -32,
      -38,
      -48,
      -61,
      -69,
      -69,
      -63,
      -52,
      -48,
      -39,
      -33,
      -27,
      -19,
      -11,
      -7
    ],
    "Dew": [
      18,
      18,
      16,
      10,
      7,
      4,
      -2,
      -10,
      -13,
      -19,
      -23,
      -31,
      -37,
      -40,
      -48,
      -54,
      -60,
      -68,
      -72,
      -75,
      -82,
      -85,
      -86,
      -89,
      -90,
      9999,
      9999,
      9999,
      9999,
      9999,
      9999
    ],
    "WindDir": [
      414,
      357,
      355,
      345,
      328,
      294,
      265,
      243,
      238,
      241,
      240,
      246,
      252,
      256,
      257,
      262,
      240,
      235,
      215,
      206,
      159,
      118,
      100,
      56,
      94,
      82,
      91,
      98,
      84,
      92,
      88
    ],
    "WindSpeed": [
      8,
      9,
      9,
      9,
      9,
      8,
      9,
      12,
      15,
      19,
      25,
      27,
      27,
      24,
      23,
      26,
      34,
      35,
      33,
      29,
      16,
      19,
      30,
      29,
      45,
      49,
      45,
      51,
      45,
      62,
      73
    ]
  }
