{
    "Time": "2021-06-14T19:00:00Z",
    "Pressure": [
      1000,
      975,
      950,
      925,
      900,
      850,
      800,
      750,
      700,
      650,
      600,
      550,
      500,
      450,
      400,
      350,
      300,
      250,
      200,
      150,
      100,
      70,
      50,
      30,
      20,
      10,
      7,
      5,
      3,
      2,
      1
    ],
    "Height": [
      344,
      1066,
      1801,
      2551,
      3315,
      4903,
      6576,
      8343,
      10215,
      12207,
      14334,
      16614,
      19065,
      21734,
      24663,
      27923,
      31598,
      35776,
      40675,
      46734,
      54762,
      61686,
      68388,
      79038,
      87724,
      103060,
      111109,
      118849,
      131000,
      140985,
      158503
    ],
    "Temp": [
      22,
      21,
      18,
      16,
      15,
      14,
      12,
      10,
      7,
      4,
      1,
      -3,
      -7,
      -11,
      -16,
      -20,
      -29,
      -38,
      -49,
      -59,
      -72,
      -68,
      -62,
      -52,
      -46,
      -39,
      -36,
      -31,
      -19,
      -14,
      -7
    ],
    "Dew": [
      15,
      15,
      14,
      14,
      10,
      -2,
      -9,
      -14,
      -20,
      -27,
      -33,
      -42,
      -45,
      -52,
      -55,
      -51,
      -45,
      -52,
      -66,
      -80,
      -83,
      -85,
      -86,
      -89,
      -93,
      9999,
      9999,
      9999,
      9999,
      9999,
      9999
    ],
    "WindDir": [
      316,
      319,
      319,
      318,
      315,
      301,
      284,
      277,
      271,
      263,
      257,
      257,
      260,
      246,
      238,
      229,
      227,
      226,
      219,
      214,
      202,
      163,
      111,
      84,
      91,
      89,
      77,
      77,
      82,
      85,
      90
    ],
    "WindSpeed": [
      6,
      11,
      11,
      11,
      12,
      14,
      16,
      19,
      22,
      24,
      26,
      28,
      33,
      51,
      63,
      81,
      88,
      87,
      83,
      66,
      55,
      17,
      26,
      31,
      34,
      44,
      41,
      51,
      58,
      65,
      68
    ]
  }
