{
    "Time": "2021-06-27T20:00:00Z",
    "Pressure": [
      1000,
      975,
      950,
      925,
      900,
      850,
      800,
      750,
      700,
      650,
      600,
      550,
      500,
      450,
      400,
      350,
      300,
      250,
      200,
      150,
      100,
      70,
      50,
      30,
      20,
      10,
      7,
      5,
      3,
      2,
      1
    ],
    "Height": [
      197,
      929,
      1680,
      2456,
      3246,
      4890,
      6613,
      8421,
      10331,
      12361,
      14517,
      16831,
      19319,
      21996,
      24921,
      28198,
      31889,
      36103,
      41030,
      47038,
      55016,
      61942,
      68647,
      79250,
      87861,
      103147,
      111105,
      118903,
      131344,
      141391,
      159081
    ],
    "Temp": [
      26,
      25,
      26,
      26,
      26,
      23,
      19,
      16,
      13,
      9,
      5,
      1,
      -4,
      -11,
      -16,
      -19,
      -27,
      -37,
      -48,
      -62,
      -71,
      -69,
      -61,
      -52,
      -51,
      -41,
      -37,
      -25,
      -16,
      -13,
      -4
    ],
    "Dew": [
      20,
      18,
      12,
      9,
      7,
      6,
      4,
      -2,
      -10,
      -19,
      -30,
      -42,
      -44,
      -48,
      -59,
      -63,
      -57,
      -62,
      -70,
      -76,
      -82,
      -85,
      -87,
      -90,
      -95,
      11120,
      9999,
      9999,
      9999,
      9999,
      9999
    ],
    "WindDir": [
      327,
      342,
      341,
      337,
      333,
      330,
      330,
      297,
      275,
      271,
      264,
      258,
      274,
      251,
      265,
      265,
      267,
      263,
      265,
      244,
      211,
      111,
      100,
      81,
      91,
      80,
      84,
      102,
      81,
      91,
      91
    ],
    "WindSpeed": [
      3,
      6,
      11,
      14,
      14,
      12,
      9,
      6,
      9,
      11,
      12,
      12,
      16,
      23,
      28,
      41,
      49,
      45,
      48,
      40,
      9,
      18,
      20,
      22,
      35,
      27,
      44,
      54,
      50,
      62,
      68
    ]
  }
