{
    "Time": "2021-06-10T20:00:00Z",
    "Pressure": [
      1000,
      975,
      950,
      925,
      900,
      850,
      800,
      750,
      700,
      650,
      600,
      550,
      500,
      450,
      400,
      350,
      300,
      250,
      200,
      150,
      100,
      70,
      50,
      30,
      20,
      10,
      7,
      5,
      3,
      2,
      1
    ],
    "Height": [
      344,
      1063,
      1801,
      2550,
      3318,
      4918,
      6607,
      8380,
      10255,
      12255,
      14387,
      16672,
      19141,
      21806,
      24709,
      27906,
      31479,
      35555,
      40431,
      46495,
      54626,
      61553,
      68265,
      78857,
      87511,
      102633,
      110659,
      118455,
      130688,
      140729,
      158415
    ],
    "Temp": [
      22,
      21,
      19,
      17,
      17,
      17,
      14,
      10,
      8,
      6,
      1,
      -1,
      -6,
      -12,
      -20,
      -27,
      -36,
      -44,
      -47,
      -59,
      -69,
      -67,
      -60,
      -53,
      -48,
      -41,
      -35,
      -28,
      -19,
      -11,
      -7
    ],
    "Dew": [
      17,
      16,
      16,
      14,
      7,
      1,
      -4,
      -15,
      -29,
      -35,
      -32,
      -34,
      -24,
      -36,
      -46,
      -43,
      -39,
      -51,
      -73,
      -79,
      -83,
      -85,
      -86,
      -89,
      -90,
      9999,
      9999,
      9999,
      9999,
      9999,
      9999
    ],
    "WindDir": [
      269,
      275,
      274,
      273,
      279,
      273,
      257,
      256,
      263,
      268,
      266,
      258,
      257,
      248,
      244,
      246,
      244,
      244,
      235,
      233,
      205,
      159,
      91,
      86,
      81,
      101,
      78,
      82,
      81,
      90,
      80
    ],
    "WindSpeed": [
      4,
      6,
      6,
      8,
      15,
      27,
      36,
      38,
      37,
      37,
      35,
      43,
      45,
      51,
      53,
      55,
      65,
      76,
      73,
      61,
      25,
      10,
      8,
      23,
      25,
      18,
      25,
      32,
      50,
      57,
      49
    ]
  }
