{
    "Time": "2021-07-17T23:00:00Z",
    "Pressure": [
      1000,
      975,
      950,
      925,
      900,
      850,
      800,
      750,
      700,
      650,
      600,
      550,
      500,
      450,
      400,
      350,
      300,
      250,
      200,
      150,
      100,
      70,
      50,
      30,
      20,
      10,
      7,
      5,
      3,
      2,
      1
    ],
    "Height": [
      114,
      830,
      1583,
      2359,
      3158,
      4809,
      6542,
      8367,
      10285,
      12317,
      14479,
      16805,
      19320,
      22065,
      25074,
      28404,
      32131,
      36366,
      41340,
      47411,
      55413,
      62204,
      68925,
      79576,
      88232,
      103431,
      111399,
      119086,
      131263,
      141259,
      159046
    ],
    "Temp": [
      29,
      28,
      27,
      28,
      27,
      25,
      21,
      17,
      13,
      8,
      7,
      3,
      0,
      -4,
      -9,
      -17,
      -25,
      -36,
      -46,
      -60,
      -74,
      -70,
      -61,
      -52,
      -49,
      -41,
      -40,
      -29,
      -20,
      -10,
      -7
    ],
    "Dew": [
      17,
      16,
      14,
      7,
      3,
      1,
      7,
      4,
      1,
      -1,
      -31,
      -43,
      -50,
      -49,
      -51,
      -55,
      -51,
      -56,
      -65,
      -71,
      -82,
      -85,
      -87,
      -90,
      -91,
      9999,
      9999,
      9999,
      9999,
      9999,
      9999
    ],
    "WindDir": [
      317,
      318,
      324,
      327,
      326,
      275,
      334,
      109,
      125,
      120,
      35,
      352,
      438,
      321,
      339,
      299,
      288,
      296,
      282,
      317,
      150,
      118,
      102,
      99,
      83,
      84,
      93,
      95,
      75,
      82,
      89
    ],
    "WindSpeed": [
      7,
      7,
      8,
      7,
      7,
      5,
      2,
      10,
      21,
      20,
      8,
      12,
      13,
      14,
      6,
      14,
      15,
      13,
      16,
      9,
      12,
      22,
      32,
      29,
      54,
      50,
      55,
      59,
      53,
      71,
      77
    ]
  }
