{
    "Time": "2020-08-25T00:00:00Z",
    "Pressure": [
      1000,
      975,
      950,
      925,
      900,
      850,
      800,
      750,
      700,
      650,
      600,
      550,
      500,
      450,
      400,
      350,
      300,
      250,
      200,
      150,
      100,
      70,
      50,
      30,
      20,
      10,
      7,
      5,
      3,
      2,
      1
    ],
    "Height": [
      154,
      875,
      1620,
      2385,
      3172,
      4799,
      6512,
      8320,
      10229,
      12253,
      14409,
      16715,
      19202,
      21902,
      24865,
      28146,
      31827,
      36046,
      40987,
      47043,
      55045,
      61883,
      68500,
      78956,
      87486,
      102467,
      110360,
      118021,
      130223,
      140203,
      157500
    ],
    "Temp": [
      25,
      24,
      23,
      24,
      23,
      21,
      19,
      16,
      13,
      9,
      5,
      0,
      -4,
      -8,
      -13,
      -20,
      -28,
      -36,
      -47,
      -60,
      -71,
      -72,
      -63,
      -56,
      -51,
      -45,
      -40,
      -31,
      -19,
      -14,
      -13
    ],
    "Dew": [
      17,
      16,
      15,
      9,
      5,
      0,
      -8,
      -13,
      -21,
      -25,
      -32,
      -37,
      -43,
      -49,
      -50,
      -51,
      -56,
      -61,
      -66,
      -78,
      -81,
      -82,
      -84,
      -87,
      -90,
      -92,
      -89,
      9999,
      9999,
      9999,
      9999
    ],
    "WindDir": [
      88,
      82,
      3,
      337,
      321,
      307,
      292,
      249,
      222,
      219,
      250,
      260,
      265,
      265,
      261,
      262,
      258,
      260,
      262,
      258,
      255,
      261,
      78,
      91,
      88,
      100,
      83,
      82,
      97,
      79,
      84
    ],
    "WindSpeed": [
      2,
      2,
      4,
      7,
      10,
      13,
      12,
      9,
      11,
      10,
      10,
      13,
      19,
      30,
      40,
      42,
      44,
      44,
      42,
      43,
      20,
      6,
      12,
      27,
      27,
      26,
      33,
      48,
      32,
      32,
      52
    ]
  }
