{
    "Time": "2021-04-27T03:00:00Z",
    "Pressure": [
      1000,
      975,
      950,
      925,
      900,
      850,
      800,
      750,
      700,
      650,
      600,
      550,
      500,
      450,
      400,
      350,
      300,
      250,
      200,
      150,
      100,
      70,
      50,
      30,
      20,
      10,
      7,
      5,
      3,
      2,
      1
    ],
    "Height": [
      380,
      1089,
      1807,
      2542,
      3293,
      4845,
      6489,
      8231,
      10085,
      12057,
      14156,
      16397,
      18799,
      21391,
      24215,
      27319,
      30770,
      34708,
      39429,
      45433,
      53743,
      60885,
      67637,
      78136,
      86640,
      101528,
      109438,
      117040,
      129025,
      138799,
      156112
    ],
    "Temp": [
      16,
      15,
      13,
      11,
      9,
      8,
      7,
      7,
      5,
      2,
      -2,
      -7,
      -13,
      -20,
      -27,
      -34,
      -44,
      -50,
      -55,
      -54,
      -64,
      -64,
      -62,
      -56,
      -53,
      -44,
      -40,
      -34,
      -25,
      -17,
      -11
    ],
    "Dew": [
      11,
      10,
      10,
      9,
      9,
      1,
      -6,
      -24,
      -37,
      -44,
      -46,
      -45,
      -50,
      -45,
      -46,
      -54,
      -51,
      -62,
      -68,
      -79,
      -82,
      -85,
      -86,
      -88,
      -91,
      -91,
      9999,
      9999,
      9999,
      9999,
      9999
    ],
    "WindDir": [
      221,
      223,
      226,
      228,
      234,
      300,
      317,
      316,
      314,
      318,
      316,
      316,
      316,
      320,
      314,
      320,
      320,
      321,
      306,
      276,
      277,
      232,
      140,
      75,
      71,
      64,
      60,
      45,
      38,
      79,
      36
    ],
    "WindSpeed": [
      6,
      7,
      8,
      8,
      8,
      11,
      16,
      18,
      23,
      24,
      27,
      32,
      32,
      35,
      32,
      35,
      39,
      50,
      48,
      40,
      27,
      6,
      1,
      7,
      21,
      19,
      13,
      16,
      15,
      21,
      9
    ]
  }
