{
    "Time": "2021-03-27T09:00:00Z",
    "Pressure": [
      1000,
      975,
      950,
      925,
      900,
      850,
      800,
      750,
      700,
      650,
      600,
      550,
      500,
      450,
      400,
      350,
      300,
      250,
      200,
      150,
      100,
      70,
      50,
      30,
      20,
      10,
      7,
      5,
      3,
      2,
      1
    ],
    "Height": [
      708,
      1400,
      2106,
      2828,
      3559,
      5072,
      6663,
      8346,
      10134,
      12043,
      14091,
      16279,
      18645,
      21220,
      24058,
      27234,
      30823,
      34973,
      39855,
      45856,
      53933,
      60859,
      67516,
      78113,
      86830,
      101971,
      109996,
      117834,
      130078,
      139977,
      157103
    ],
    "Temp": [
      12,
      10,
      8,
      6,
      4,
      0,
      0,
      -2,
      -4,
      -5,
      -9,
      -13,
      -16,
      -20,
      -24,
      -27,
      -34,
      -39,
      -50,
      -61,
      -71,
      -69,
      -64,
      -52,
      -47,
      -41,
      -35,
      -26,
      -21,
      -16,
      -14
    ],
    "Dew": [
      1,
      1,
      0,
      0,
      0,
      -3,
      -29,
      -32,
      -27,
      -29,
      -37,
      -48,
      -51,
      -53,
      -54,
      -52,
      -49,
      -67,
      -73,
      -77,
      -82,
      -84,
      -86,
      -89,
      -90,
      9999,
      9999,
      9999,
      9999,
      9999,
      9999
    ],
    "WindDir": [
      321,
      322,
      323,
      324,
      325,
      326,
      320,
      309,
      303,
      312,
      306,
      287,
      268,
      258,
      247,
      242,
      243,
      241,
      245,
      251,
      252,
      258,
      285,
      57,
      127,
      101,
      94,
      77,
      55,
      322,
      270
    ],
    "WindSpeed": [
      11,
      10,
      9,
      8,
      8,
      7,
      12,
      17,
      21,
      24,
      25,
      33,
      50,
      71,
      94,
      127,
      136,
      129,
      126,
      100,
      54,
      30,
      16,
      8,
      16,
      20,
      17,
      33,
      19,
      14,
      14
    ]
  }
