{
    "Time": "2021-07-03T00:00:00Z",
    "Pressure": [
      1000,
      975,
      950,
      925,
      900,
      850,
      800,
      750,
      700,
      650,
      600,
      550,
      500,
      450,
      400,
      350,
      300,
      250,
      200,
      150,
      100,
      70,
      50,
      30,
      20,
      10,
      7,
      5,
      3,
      2,
      1
    ],
    "Height": [
      187,
      921,
      1676,
      2450,
      3244,
      4895,
      6624,
      8435,
      10341,
      12368,
      14530,
      16843,
      19327,
      22014,
      24963,
      28218,
      31870,
      36043,
      40964,
      46988,
      54977,
      61830,
      68477,
      79035,
      87719,
      102956,
      110984,
      118687,
      130853,
      140987,
      158717
    ],
    "Temp": [
      27,
      27,
      28,
      27,
      27,
      25,
      20,
      16,
      13,
      10,
      5,
      1,
      -4,
      -9,
      -15,
      -23,
      -30,
      -39,
      -48,
      -61,
      -72,
      -71,
      -62,
      -53,
      -47,
      -40,
      -37,
      -31,
      -18,
      -8,
      -7
    ],
    "Dew": [
      16,
      13,
      8,
      6,
      4,
      -1,
      -2,
      -10,
      -23,
      -32,
      -39,
      -38,
      -45,
      -51,
      -47,
      -52,
      -57,
      -61,
      -70,
      -79,
      -82,
      -84,
      -86,
      -89,
      -93,
      9999,
      9999,
      9999,
      9999,
      9999,
      9999
    ],
    "WindDir": [
      199,
      213,
      248,
      279,
      295,
      311,
      326,
      328,
      320,
      298,
      278,
      272,
      272,
      253,
      246,
      247,
      232,
      236,
      231,
      223,
      196,
      131,
      87,
      89,
      95,
      90,
      96,
      88,
      89,
      101,
      82
    ],
    "WindSpeed": [
      4,
      5,
      5,
      6,
      8,
      11,
      13,
      16,
      16,
      14,
      16,
      19,
      20,
      24,
      33,
      36,
      39,
      43,
      58,
      52,
      24,
      10,
      23,
      37,
      34,
      46,
      50,
      62,
      72,
      76,
      74
    ]
  }
