{
    "Time": "2021-06-28T22:00:00Z",
    "Pressure": [
      1000,
      975,
      950,
      925,
      900,
      850,
      800,
      750,
      700,
      650,
      600,
      550,
      500,
      450,
      400,
      350,
      300,
      250,
      200,
      150,
      100,
      70,
      50,
      30,
      20,
      10,
      7,
      5,
      3,
      2,
      1
    ],
    "Height": [
      224,
      957,
      1708,
      2480,
      3271,
      4912,
      6636,
      8453,
      10366,
      12399,
      14557,
      16861,
      19337,
      22020,
      24977,
      28269,
      31954,
      36161,
      41110,
      47108,
      55088,
      61960,
      68626,
      79234,
      87847,
      103095,
      111241,
      119045,
      131326,
      141412,
      159122
    ],
    "Temp": [
      28,
      27,
      26,
      26,
      25,
      23,
      20,
      17,
      13,
      10,
      5,
      0,
      -5,
      -10,
      -13,
      -19,
      -28,
      -37,
      -48,
      -62,
      -72,
      -71,
      -62,
      -54,
      -48,
      -38,
      -34,
      -29,
      -16,
      -13,
      -5
    ],
    "Dew": [
      17,
      16,
      13,
      10,
      8,
      5,
      -11,
      -16,
      -28,
      -37,
      -38,
      -44,
      -49,
      -56,
      -57,
      -52,
      -57,
      -65,
      -70,
      -76,
      -81,
      -85,
      -90,
      -89,
      -90,
      9999,
      9999,
      9999,
      9999,
      9999,
      9999
    ],
    "WindDir": [
      -21,
      -24,
      368,
      340,
      333,
      329,
      283,
      239,
      240,
      260,
      271,
      264,
      266,
      275,
      277,
      274,
      275,
      273,
      269,
      268,
      269,
      103,
      92,
      83,
      89,
      127,
      80,
      85,
      74,
      75,
      101
    ],
    "WindSpeed": [
      3,
      4,
      5,
      9,
      11,
      10,
      7,
      9,
      11,
      12,
      14,
      18,
      17,
      24,
      42,
      49,
      46,
      39,
      37,
      29,
      3,
      13,
      22,
      26,
      35,
      30,
      39,
      53,
      45,
      68,
      61
    ]
  }
