{
    "Time": "2020-08-09T21:00:00Z",
    "Pressure": [
      1000,
      975,
      950,
      925,
      900,
      850,
      800,
      750,
      700,
      650,
      600,
      550,
      500,
      450,
      400,
      350,
      300,
      250,
      200,
      150,
      100,
      70,
      50,
      30,
      20,
      10,
      7,
      5,
      3,
      2,
      1
    ],
    "Height": [
      223,
      944,
      1689,
      2447,
      3221,
      4826,
      6525,
      8320,
      10223,
      12247,
      14416,
      16738,
      19245,
      21975,
      24960,
      28267,
      32001,
      36259,
      41250,
      47349,
      55295,
      62043,
      68664,
      79114,
      87687,
      102834,
      110839,
      118520,
      130669,
      140623,
      158031
    ],
    "Temp": [
      24,
      23,
      21,
      19,
      17,
      18,
      16,
      15,
      12,
      9,
      7,
      2,
      -1,
      -5,
      -12,
      -17,
      -25,
      -34,
      -45,
      -60,
      -74,
      -74,
      -64,
      -56,
      -49,
      -41,
      -37,
      -32,
      -20,
      -14,
      -11
    ],
    "Dew": [
      20,
      19,
      18,
      18,
      16,
      4,
      -3,
      -11,
      -20,
      -29,
      -35,
      -39,
      -45,
      -50,
      -54,
      -51,
      -47,
      -45,
      -56,
      -65,
      -79,
      -83,
      -85,
      -88,
      -91,
      -90,
      9999,
      9999,
      9999,
      9999,
      9999
    ],
    "WindDir": [
      201,
      212,
      254,
      268,
      273,
      278,
      280,
      282,
      278,
      272,
      266,
      264,
      265,
      264,
      256,
      250,
      238,
      229,
      226,
      201,
      190,
      163,
      99,
      88,
      89,
      91,
      88,
      79,
      81,
      84,
      80
    ],
    "WindSpeed": [
      5,
      5,
      7,
      9,
      10,
      18,
      21,
      18,
      18,
      20,
      20,
      21,
      20,
      19,
      22,
      28,
      28,
      33,
      34,
      37,
      40,
      18,
      22,
      32,
      37,
      32,
      41,
      46,
      51,
      56,
      59
    ]
  }
