{
    "Time": "2021-06-27T10:00:00Z",
    "Pressure": [
      1000,
      975,
      950,
      925,
      900,
      850,
      800,
      750,
      700,
      650,
      600,
      550,
      500,
      450,
      400,
      350,
      300,
      250,
      200,
      150,
      100,
      70,
      50,
      30,
      20,
      10,
      7,
      5,
      3,
      2,
      1
    ],
    "Height": [
      202,
      934,
      1695,
      2466,
      3255,
      4884,
      6592,
      8391,
      10296,
      12325,
      14487,
      16797,
      19284,
      21967,
      24887,
      28160,
      31851,
      36068,
      41009,
      47021,
      54998,
      61837,
      68516,
      79110,
      87791,
      103018,
      110986,
      118778,
      131076,
      141099,
      158627
    ],
    "Temp": [
      32,
      30,
      27,
      25,
      23,
      20,
      17,
      14,
      12,
      10,
      5,
      1,
      -4,
      -11,
      -16,
      -19,
      -27,
      -36,
      -48,
      -61,
      -73,
      -70,
      -62,
      -52,
      -48,
      -42,
      -37,
      -26,
      -19,
      -11,
      -10
    ],
    "Dew": [
      14,
      13,
      12,
      12,
      11,
      6,
      2,
      -8,
      -19,
      -28,
      -33,
      -42,
      -49,
      -48,
      -54,
      -60,
      -60,
      -63,
      -71,
      -76,
      -82,
      -85,
      -86,
      -89,
      -94,
      9999,
      9999,
      9999,
      9999,
      9999,
      9999
    ],
    "WindDir": [
      286,
      285,
      284,
      285,
      289,
      349,
      346,
      304,
      273,
      274,
      259,
      258,
      279,
      264,
      258,
      260,
      264,
      261,
      256,
      233,
      244,
      124,
      111,
      104,
      93,
      86,
      102,
      95,
      95,
      93,
      94
    ],
    "WindSpeed": [
      7,
      7,
      6,
      5,
      4,
      6,
      8,
      7,
      7,
      6,
      7,
      9,
      7,
      6,
      25,
      43,
      47,
      58,
      52,
      37,
      18,
      14,
      22,
      30,
      31,
      29,
      42,
      52,
      60,
      57,
      89
    ]
  }
