{
    "Time": "2021-05-25T18:00:00Z",
    "Pressure": [
      1000,
      975,
      950,
      925,
      900,
      850,
      800,
      750,
      700,
      650,
      600,
      550,
      500,
      450,
      400,
      350,
      300,
      250,
      200,
      150,
      100,
      70,
      50,
      30,
      20,
      10,
      7,
      5,
      3,
      2,
      1
    ],
    "Height": [
      337,
      1059,
      1801,
      2559,
      3339,
      4957,
      6656,
      8444,
      10337,
      12349,
      14498,
      16797,
      19261,
      21919,
      24806,
      27979,
      31509,
      35511,
      40187,
      46003,
      54173,
      61272,
      68083,
      78746,
      87414,
      102726,
      110715,
      118458,
      130603,
      140538,
      158480
    ],
    "Temp": [
      22,
      21,
      22,
      22,
      21,
      19,
      16,
      13,
      10,
      7,
      4,
      0,
      -7,
      -14,
      -21,
      -30,
      -39,
      -49,
      -59,
      -64,
      -65,
      -65,
      -58,
      -53,
      -46,
      -40,
      -37,
      -29,
      -23,
      -10,
      -2
    ],
    "Dew": [
      17,
      14,
      7,
      5,
      5,
      1,
      -4,
      -10,
      -11,
      -21,
      -26,
      -28,
      -33,
      -40,
      -44,
      -46,
      -48,
      -58,
      -64,
      -72,
      -82,
      -85,
      -86,
      -90,
      -92,
      9999,
      9999,
      9999,
      9999,
      9999,
      9999
    ],
    "WindDir": [
      340,
      339,
      330,
      327,
      333,
      344,
      330,
      316,
      330,
      334,
      334,
      313,
      319,
      314,
      307,
      291,
      267,
      291,
      314,
      284,
      278,
      80,
      84,
      75,
      81,
      86,
      83,
      80,
      66,
      84,
      99
    ],
    "WindSpeed": [
      3,
      8,
      11,
      14,
      17,
      24,
      16,
      9,
      9,
      12,
      14,
      11,
      8,
      12,
      17,
      16,
      22,
      21,
      13,
      21,
      19,
      7,
      6,
      17,
      27,
      32,
      35,
      41,
      44,
      43,
      41
    ]
  }
