{
    "Time": "2021-07-02T13:00:00Z",
    "Pressure": [
      1000,
      975,
      950,
      925,
      900,
      850,
      800,
      750,
      700,
      650,
      600,
      550,
      500,
      450,
      400,
      350,
      300,
      250,
      200,
      150,
      100,
      70,
      50,
      30,
      20,
      10,
      7,
      5,
      3,
      2,
      1
    ],
    "Height": [
      194,
      918,
      1680,
      2463,
      3261,
      4911,
      6638,
      8452,
      10365,
      12396,
      14554,
      16858,
      19335,
      22009,
      24941,
      28197,
      31849,
      36025,
      40940,
      46984,
      55011,
      61870,
      68557,
      79143,
      87858,
      103093,
      111144,
      118916,
      131212,
      141334,
      158918
    ],
    "Temp": [
      35,
      34,
      32,
      30,
      28,
      24,
      20,
      17,
      13,
      10,
      5,
      0,
      -5,
      -11,
      -15,
      -23,
      -30,
      -39,
      -48,
      -60,
      -72,
      -71,
      -62,
      -53,
      -47,
      -40,
      -35,
      -29,
      -15,
      -10,
      -7
    ],
    "Dew": [
      11,
      10,
      9,
      8,
      7,
      5,
      2,
      -9,
      -27,
      -36,
      -39,
      -42,
      -47,
      -51,
      -52,
      -50,
      -57,
      -63,
      -68,
      -78,
      -82,
      -84,
      -86,
      -89,
      -93,
      9999,
      9999,
      9999,
      9999,
      9999,
      9999
    ],
    "WindDir": [
      294,
      294,
      296,
      299,
      302,
      316,
      348,
      352,
      318,
      270,
      255,
      255,
      264,
      258,
      248,
      248,
      238,
      233,
      227,
      226,
      198,
      130,
      102,
      99,
      95,
      95,
      99,
      96,
      97,
      91,
      93
    ],
    "WindSpeed": [
      11,
      11,
      13,
      13,
      13,
      12,
      11,
      9,
      5,
      7,
      10,
      12,
      12,
      17,
      43,
      48,
      48,
      47,
      47,
      44,
      20,
      18,
      24,
      35,
      30,
      44,
      43,
      59,
      62,
      73,
      93
    ]
  }
