{
    "Time": "2020-08-26T06:00:00Z",
    "Pressure": [
      1000,
      975,
      950,
      925,
      900,
      850,
      800,
      750,
      700,
      650,
      600,
      550,
      500,
      450,
      400,
      350,
      300,
      250,
      200,
      150,
      100,
      70,
      50,
      30,
      20,
      10,
      7,
      5,
      3,
      2,
      1
    ],
    "Height": [
      249,
      980,
      1725,
      2483,
      3264,
      4891,
      6597,
      8398,
      10305,
      12326,
      14481,
      16791,
      19288,
      21991,
      24954,
      28228,
      31906,
      36118,
      41046,
      47066,
      55039,
      61886,
      68487,
      78956,
      87513,
      102559,
      110534,
      118218,
      130213,
      139993,
      157276
    ],
    "Temp": [
      26,
      23,
      21,
      21,
      22,
      20,
      18,
      16,
      13,
      9,
      5,
      1,
      -3,
      -8,
      -14,
      -21,
      -28,
      -37,
      -49,
      -61,
      -73,
      -72,
      -63,
      -56,
      -51,
      -42,
      -37,
      -33,
      -25,
      -17,
      -11
    ],
    "Dew": [
      20,
      19,
      18,
      14,
      5,
      1,
      -9,
      -18,
      -22,
      -32,
      -35,
      -38,
      -39,
      -43,
      -44,
      -46,
      -54,
      -56,
      -63,
      -76,
      -81,
      -81,
      -84,
      -87,
      -90,
      -90,
      9999,
      9999,
      9999,
      9999,
      9999
    ],
    "WindDir": [
      205,
      209,
      327,
      3,
      6,
      16,
      351,
      246,
      206,
      228,
      251,
      284,
      289,
      271,
      266,
      262,
      259,
      261,
      232,
      231,
      205,
      94,
      88,
      86,
      102,
      87,
      93,
      98,
      88,
      91,
      105
    ],
    "WindSpeed": [
      3,
      2,
      1,
      5,
      7,
      8,
      4,
      4,
      8,
      6,
      10,
      15,
      19,
      25,
      32,
      34,
      35,
      37,
      36,
      44,
      20,
      13,
      24,
      30,
      29,
      32,
      37,
      42,
      52,
      52,
      49
    ]
  }
