{
    "Time": "2021-07-18T12:00:00Z",
    "Pressure": [
      1000,
      975,
      950,
      925,
      900,
      850,
      800,
      750,
      700,
      650,
      600,
      550,
      500,
      450,
      400,
      350,
      300,
      250,
      200,
      150,
      100,
      70,
      50,
      30,
      20,
      10,
      7,
      5,
      3,
      2,
      1
    ],
    "Height": [
      101,
      839,
      1597,
      2372,
      3162,
      4812,
      6551,
      8379,
      10308,
      12345,
      14504,
      16817,
      19327,
      22066,
      25078,
      28418,
      32145,
      36374,
      41341,
      47411,
      55393,
      62148,
      68809,
      79448,
      88090,
      103182,
      111200,
      118904,
      131102,
      141243,
      158923
    ],
    "Temp": [
      32,
      29,
      27,
      26,
      25,
      25,
      23,
      19,
      15,
      9,
      5,
      2,
      0,
      -4,
      -9,
      -16,
      -26,
      -36,
      -46,
      -60,
      -74,
      -73,
      -61,
      -53,
      -49,
      -41,
      -37,
      -30,
      -17,
      -8,
      -8
    ],
    "Dew": [
      18,
      17,
      15,
      14,
      9,
      -7,
      -6,
      -5,
      -3,
      -7,
      -27,
      -44,
      -50,
      -47,
      -53,
      -56,
      -53,
      -59,
      -69,
      -70,
      -81,
      -85,
      -87,
      -91,
      -91,
      9999,
      9999,
      9999,
      9999,
      9999,
      9999
    ],
    "WindDir": [
      306,
      310,
      313,
      310,
      286,
      219,
      216,
      232,
      231,
      239,
      205,
      156,
      55,
      134,
      183,
      209,
      209,
      222,
      224,
      138,
      123,
      117,
      98,
      94,
      93,
      89,
      98,
      96,
      92,
      88,
      88
    ],
    "WindSpeed": [
      10,
      10,
      9,
      7,
      5,
      8,
      15,
      21,
      27,
      32,
      17,
      2,
      4,
      5,
      8,
      11,
      9,
      8,
      10,
      5,
      23,
      31,
      35,
      33,
      36,
      49,
      44,
      49,
      67,
      57,
      81
    ]
  }
