{
    "Time": "2021-06-21T14:00:00Z",
    "Pressure": [
      1000,
      975,
      950,
      925,
      900,
      850,
      800,
      750,
      700,
      650,
      600,
      550,
      500,
      450,
      400,
      350,
      300,
      250,
      200,
      150,
      100,
      70,
      50,
      30,
      20,
      10,
      7,
      5,
      3,
      2,
      1
    ],
    "Height": [
      311,
      1040,
      1781,
      2538,
      3312,
      4914,
      6601,
      8380,
      10258,
      12253,
      14379,
      16656,
      19107,
      21766,
      24662,
      27848,
      31420,
      35527,
      40425,
      46524,
      54719,
      61717,
      68425,
      78990,
      87688,
      102914,
      110961,
      118803,
      131109,
      141118,
      158764
    ],
    "Temp": [
      25,
      23,
      21,
      20,
      18,
      16,
      14,
      11,
      8,
      5,
      1,
      -2,
      -7,
      -13,
      -20,
      -28,
      -35,
      -41,
      -46,
      -57,
      -67,
      -68,
      -62,
      -53,
      -47,
      -39,
      -35,
      -25,
      -18,
      -11,
      -6
    ],
    "Dew": [
      15,
      15,
      14,
      11,
      9,
      4,
      1,
      -3,
      -8,
      -14,
      -19,
      -31,
      -38,
      -36,
      -37,
      -49,
      -57,
      -63,
      -71,
      -79,
      -83,
      -85,
      -87,
      -90,
      -90,
      9999,
      9999,
      9999,
      9999,
      9999,
      9999
    ],
    "WindDir": [
      304,
      304,
      303,
      297,
      286,
      259,
      248,
      246,
      241,
      231,
      224,
      224,
      225,
      218,
      216,
      215,
      218,
      205,
      203,
      218,
      195,
      156,
      115,
      99,
      89,
      86,
      92,
      96,
      91,
      83,
      94
    ],
    "WindSpeed": [
      9,
      11,
      10,
      9,
      8,
      11,
      14,
      16,
      18,
      22,
      24,
      27,
      33,
      40,
      42,
      40,
      42,
      56,
      63,
      56,
      29,
      19,
      25,
      29,
      23,
      39,
      47,
      45,
      45,
      57,
      81
    ]
  }
