{
    "Time": "2021-01-08T18:00:00Z",
    "Pressure": [
      1000,
      975,
      950,
      925,
      900,
      850,
      800,
      750,
      700,
      650,
      600,
      550,
      500,
      450,
      400,
      350,
      300,
      250,
      200,
      150,
      100,
      70,
      50,
      30,
      20,
      10,
      7,
      5,
      3,
      2,
      1
    ],
    "Height": [
      544,
      1246,
      1968,
      2709,
      3464,
      5026,
      6660,
      8379,
      10200,
      12122,
      14176,
      16381,
      18753,
      21318,
      24114,
      27198,
      30636,
      34534,
      39146,
      45042,
      53261,
      60370,
      67165,
      77742,
      86233,
      101131,
      108966,
      116476,
      128375,
      138136,
      155656
    ],
    "Temp": [
      17,
      15,
      15,
      14,
      12,
      8,
      5,
      3,
      0,
      -4,
      -7,
      -11,
      -16,
      -22,
      -29,
      -36,
      -45,
      -55,
      -59,
      -60,
      -64,
      -64,
      -61,
      -54,
      -54,
      -44,
      -43,
      -36,
      -26,
      -16,
      -6
    ],
    "Dew": [
      1,
      0,
      -1,
      -2,
      -3,
      -4,
      -8,
      -12,
      -16,
      -20,
      -25,
      -27,
      -25,
      -25,
      -30,
      -36,
      -45,
      -55,
      -68,
      -76,
      -80,
      -81,
      -82,
      -85,
      -88,
      -91,
      9999,
      9999,
      9999,
      9999,
      9999
    ],
    "WindDir": [
      90,
      90,
      87,
      92,
      101,
      108,
      127,
      147,
      258,
      319,
      315,
      310,
      304,
      310,
      299,
      301,
      300,
      287,
      299,
      298,
      295,
      293,
      275,
      263,
      270,
      273,
      268,
      273,
      278,
      265,
      290
    ],
    "WindSpeed": [
      5,
      5,
      16,
      19,
      19,
      14,
      10,
      4,
      0,
      4,
      9,
      14,
      16,
      19,
      20,
      26,
      28,
      29,
      50,
      62,
      44,
      29,
      19,
      30,
      36,
      45,
      56,
      50,
      28,
      32,
      52
    ]
  }
