{
    "Time": "2021-02-15T00:00:00Z",
    "Pressure": [
      1000,
      975,
      950,
      925,
      900,
      850,
      800,
      750,
      700,
      650,
      600,
      550,
      500,
      450,
      400,
      350,
      300,
      250,
      200,
      150,
      100,
      70,
      50,
      30,
      20,
      10,
      7,
      5,
      3,
      2,
      1
    ],
    "Height": [
      433,
      1135,
      1847,
      2575,
      3323,
      4875,
      6519,
      8254,
      10091,
      12037,
      14104,
      16309,
      18677,
      21243,
      24045,
      27145,
      30620,
      34639,
      39491,
      45515,
      53615,
      60577,
      67178,
      77486,
      85843,
      100524,
      108382,
      115954,
      127874,
      137851,
      155456
    ],
    "Temp": [
      14,
      13,
      11,
      9,
      10,
      8,
      8,
      5,
      2,
      -1,
      -6,
      -11,
      -17,
      -22,
      -28,
      -34,
      -41,
      -44,
      -50,
      -59,
      -68,
      -70,
      -65,
      -60,
      -56,
      -47,
      -40,
      -37,
      -22,
      -13,
      -6
    ],
    "Dew": [
      10,
      10,
      9,
      6,
      -4,
      -8,
      -27,
      -35,
      -36,
      -34,
      -28,
      -36,
      -45,
      -49,
      -52,
      -53,
      -59,
      -65,
      -73,
      -77,
      -81,
      -82,
      -84,
      -89,
      -90,
      -93,
      -89,
      9999,
      9999,
      9999,
      9999
    ],
    "WindDir": [
      21,
      359,
      353,
      320,
      303,
      280,
      236,
      233,
      232,
      235,
      236,
      237,
      244,
      251,
      256,
      255,
      256,
      259,
      260,
      261,
      261,
      254,
      265,
      316,
      299,
      258,
      253,
      267,
      276,
      274,
      283
    ],
    "WindSpeed": [
      3,
      4,
      4,
      4,
      10,
      11,
      16,
      20,
      22,
      25,
      28,
      31,
      33,
      35,
      42,
      53,
      64,
      87,
      104,
      87,
      61,
      36,
      19,
      7,
      6,
      25,
      37,
      54,
      64,
      69,
      69
    ]
  }
