{
    "Time": "2020-10-25T06:00:00Z",
    "Pressure": [
      1000,
      975,
      950,
      925,
      900,
      850,
      800,
      750,
      700,
      650,
      600,
      550,
      500,
      450,
      400,
      350,
      300,
      250,
      200,
      150,
      100,
      70,
      50,
      30,
      20,
      10,
      7,
      5,
      3,
      2,
      1
    ],
    "Height": [
      321,
      1043,
      1788,
      2549,
      3326,
      4940,
      6627,
      8398,
      10262,
      12230,
      14311,
      16528,
      18904,
      21479,
      24301,
      27408,
      30879,
      34895,
      39760,
      45807,
      53999,
      61115,
      67808,
      78162,
      86643,
      101620,
      109625,
      117355,
      129465,
      139438,
      156745
    ],
    "Temp": [
      26,
      24,
      22,
      22,
      22,
      18,
      13,
      9,
      5,
      0,
      -5,
      -11,
      -16,
      -20,
      -27,
      -34,
      -42,
      -44,
      -49,
      -58,
      -64,
      -67,
      -64,
      -58,
      -52,
      -43,
      -36,
      -31,
      -20,
      -14,
      -13
    ],
    "Dew": [
      12,
      10,
      8,
      0,
      -6,
      -1,
      0,
      -1,
      -3,
      -4,
      -7,
      -13,
      -20,
      -25,
      -28,
      -34,
      -45,
      -63,
      -71,
      -75,
      -80,
      -83,
      -86,
      -88,
      -89,
      -91,
      9999,
      9999,
      9999,
      9999,
      9999
    ],
    "WindDir": [
      117,
      114,
      112,
      114,
      117,
      122,
      139,
      173,
      203,
      214,
      213,
      208,
      198,
      188,
      184,
      200,
      218,
      235,
      252,
      263,
      272,
      339,
      35,
      58,
      250,
      247,
      296,
      320,
      34,
      65,
      106
    ],
    "WindSpeed": [
      8,
      9,
      14,
      22,
      25,
      24,
      23,
      21,
      23,
      25,
      27,
      28,
      23,
      21,
      18,
      23,
      34,
      37,
      43,
      40,
      31,
      6,
      6,
      2,
      14,
      17,
      7,
      3,
      15,
      16,
      20
    ]
  }
